qmse/__init__.py
qmse/quickdb.py
qmse-0.0.1.56.dist-info/METADATA
qmse-0.0.1.56.dist-info/WHEEL
qmse-0.0.1.56.dist-info/top_level.txt
qmse-0.0.1.56.dist-info/RECORD
