Metadata-Version: 2.1
Name: qmse
Version: 0.0.1.56
Summary: qmse
Home-page: https://github.com
Author: qmse
Author-email: 
License: MIT
Classifier: Programming Language :: Python :: 3
Classifier: License :: OSI Approved :: MIT License
Classifier: Operating System :: OS Independent
